tkitLr/CyclicCosineDecayLR.py
tkitLr/__init__.py
tkitLr-0.0.0.216325705.dist-info/LICENSE
tkitLr-0.0.0.216325705.dist-info/METADATA
tkitLr-0.0.0.216325705.dist-info/WHEEL
tkitLr-0.0.0.216325705.dist-info/top_level.txt
tkitLr-0.0.0.216325705.dist-info/RECORD
